app.py
agents/OllamaAgent.py
agents/OpenAIAgent.py
helper/__init__.py
helper/setup.py
helper/tool_call.py
helper/tools.py
helper/tools_definition.py
local_agent_toolkit-0.1.3.dist-info/licenses/LICENSE
local_agent_toolkit-0.1.3.dist-info/METADATA
local_agent_toolkit-0.1.3.dist-info/WHEEL
local_agent_toolkit-0.1.3.dist-info/entry_points.txt
local_agent_toolkit-0.1.3.dist-info/top_level.txt
local_agent_toolkit-0.1.3.dist-info/RECORD
