Metadata-Version: 2.4
Name: local-agent-toolkit
Version: 0.1.3
Summary: A sophisticated AI agent toolkit supporting multiple AI providers with tool calling capabilities.
Home-page: https://technicalheist.com
Author: TechnicalHeist
Author-email: TechnicalHeist <contact@technicalheist.com>
License: MIT
Project-URL: Homepage, https://technicalheist.com
Project-URL: Repository, https://github.com/technicalheist/local-agent-toolkit
Project-URL: Issues, https://github.com/technicalheist/local-agent-toolkit/issues
Keywords: ai,agent,toolkit,ollama,openai,tool-calling,automation
Classifier: Development Status :: 3 - Alpha
Classifier: Intended Audience :: Developers
Classifier: Topic :: Software Development :: Libraries :: Python Modules
Classifier: Topic :: Scientific/Engineering :: Artificial Intelligence
Classifier: Programming Language :: Python :: 3
Classifier: Programming Language :: Python :: 3.8
Classifier: Programming Language :: Python :: 3.9
Classifier: Programming Language :: Python :: 3.10
Classifier: Programming Language :: Python :: 3.11
Classifier: Programming Language :: Python :: 3.12
Requires-Python: >=3.8
License-File: LICENSE
Requires-Dist: ollama>=0.1.0
Requires-Dist: python-dotenv>=0.19.0
Requires-Dist: requests>=2.25.0
Requires-Dist: openai>=1.0.0
Provides-Extra: dev
Requires-Dist: pytest>=6.0; extra == "dev"
Requires-Dist: pytest-cov>=2.0; extra == "dev"
Requires-Dist: black>=21.0; extra == "dev"
Requires-Dist: flake8>=3.8; extra == "dev"
Requires-Dist: build>=0.8.0; extra == "dev"
Requires-Dist: twine>=4.0.0; extra == "dev"
Dynamic: author
Dynamic: home-page
Dynamic: license-file
Dynamic: requires-python
